<LFIXML type="dnd_phrase" contact_url="http://www.laforme.net">
	<phrases>
		<phrase>
			<element>This</element>
			<element>fader</element>
			<element>allows</element>
			<element>you</element>
			<element>to</element>
			<element>decrease</element>
			<element>bass</element>
		</phrase>
		<phrase>
			<element>You</element>
			<element>may</element>
			<element>navigate</element>
			<element>audio%20files</element>
			<element>by%20using</element>
			<element>the</element>
			<element>mouse</element>
			<element>wheel</element>
		</phrase>
		<phrase>
			<element>This</element>
			<element>compression</element>
			<element>format</element>
			<element>will</element>
			<element>allow</element>
			<element>you</element>
			<element>to%20save</element>
			<element>more</element>
			<element>space</element>
		</phrase>
		<phrase>
			<element>The%20closer</element>
			<element>the%20amplitude</element>
			<element>is</element>
			<element>the%20more%20natural</element>
			<element>the%20result</element>
			<element>sounds</element>
		</phrase>
	</phrases>
	<titre>Audio%20Editing</titre>
	<soustitre></soustitre>
	<nom_exercice>Language%20Structures%20%28Mix%29%20%20</nom_exercice>
	<image_fond>images%2Fimagefond%2Eswf</image_fond>
	<texte_aide>Put%20the%20words%20in%20the%20correct%20order%3A</texte_aide>
</LFIXML>